{"title": "Decision Enabler Gap", "subtitle": "Empowering Indian professionals with intuitive, data-driven decision support.", "problem_statement": "Indian professionals lack intuitive, integrated tools for critical, data-driven decision-making, leading to uncertainty.", "theme_color": "#f97316", "accent_color": "#fb923c", "secondary_color": "#fb923c", "theme": "playful", "hero_image_url": "/static/output/hero_c770d78d-0c21-4590-97a1-9b94bcb1c4a7.png", "hero_secondary_url": "/static/output/ui_c770d78d-0c21-4590-97a1-9b94bcb1c4a7.png", "hero_details": {}, "floating_snippets": [], "artifacts": [{"type": "research_approach", "label": "Research Strategy", "title": "Methodology", "content": "Mixed Methods", "approach": {"goal": "Understand primary user needs and decision-making pain points.", "method_desc": "Best for zero-to-one product in new market entry.", "qual_method": "In-depth Interviews", "qual_result": "15-20 user sessions with professionals", "quant_method": "Online Survey", "quant_result": "150-200 participants on decision habits"}}, {"type": "behavioral_findings", "label": "Deep Research", "title": "Empathy Pillars", "pillars": [{"title": "Clarity", "insight": "Users seek clear, concise information for complex choices.", "icon": "psychology"}, {"title": "Trust", "insight": "Need reliable, verified data to make critical decisions.", "icon": "visibility"}, {"title": "Efficiency", "insight": "Time-saving tools are highly valued for busy professionals.", "icon": "speed"}]}, {"type": "hmw_questions", "label": "Strategy", "title": "Defining the Challenges", "questions": ["HMW simplify complex choices for users?", "HMW empower confident, informed decisions?", "HMW integrate diverse data for insights?"]}, {"type": "competitive", "label": "Market Context", "title": "Competitive Benchmarking", "data": [{"name": "Excel/Spreadsheets", "pros": ["Highly customizable, powerful calculations."], "cons": ["Manual data entry, steep learning curve."]}, {"name": "Traditional Advisors", "pros": ["Personalized advice, human touch."], "cons": ["Expensive, slow, limited accessibility."]}, {"name": "Generic Productivity Apps", "pros": ["Task management, basic organization."], "cons": ["No specific decision logic, limited data."]}]}, {"type": "competitor_map", "label": "Market Positioning", "title": "Decision Tool Map", "x_axis": {"title": "Data Integration", "high": "High", "med": "Med", "low": "Low"}, "y_axis": {"title": "Ease of Use", "high": "High", "med": "Med", "low": "Low"}, "points": [{"name": "Excel", "desc": "Powerful but complex data analysis.", "x": 80, "y": 20}, {"name": "Traditional Advisors", "desc": "Personalized but slow and costly.", "x": 60, "y": 40}, {"name": "Generic Productivity", "desc": "Simple but lacks deep insights.", "x": 20, "y": 60}], "solution": {"name": "Girnarsoft Decision Enabler", "desc": "Intuitive, integrated, data-driven insights.", "x": 85, "y": 85}}, {"type": "personas", "label": "Define", "title": "User Personas", "personas": [{"name": "Arjun Sharma", "gender": "Male", "age": 30, "location": "Mumbai", "occupation": "Consultant", "family": "Married", "quote": "I need data to back my every business move.", "bio": "Ambitious consultant seeking data-driven insights to advise clients effectively and grow his career.", "tech": {"internet": 5, "gadgets": 4}, "brands": ["LinkedIn"], "needs": ["Data insights", "Quick analysis"], "frustrations": ["Information overload", "Slow tools"], "photo_url": "file:///Users/ni3_kr/Documents/UX/CaseStudyBuilder/static/img/personas/India/indian_male_1.png"}, {"name": "Priya Singh", "gender": "Female", "age": 25, "location": "Bangalore", "occupation": "Startup Founder", "family": "Single", "quote": "My startup needs quick, smart decisions to scale.", "bio": "Dynamic founder needing reliable, fast decision support for critical business strategy and market entry.", "tech": {"internet": 4, "gadgets": 5}, "brands": ["Slack"], "needs": ["Market insights", "Strategic advice"], "frustrations": ["Uncertainty", "Limited resources"], "photo_url": "file:///Users/ni3_kr/Documents/UX/CaseStudyBuilder/static/img/personas/India/indian_female_2.png"}]}, {"type": "empathy_map", "label": "Deep Empathy", "title": "Empathy Mapping", "quadrants": [{"type": "SAYS", "insights": ["\"Too many options confuse me.\"", "\"Where's the reliable data?\""]}, {"type": "THINKS", "insights": ["\"Am I making the right choice?\"", "\"This decision feels overwhelming.\""]}, {"type": "DOES", "insights": ["Researches online, asks peers.", "Delays decisions, seeks external validation."]}, {"type": "FEELS", "insights": ["Anxious, overwhelmed, uncertain.", "Frustrated by information overload."]}]}, {"type": "scamper_board", "label": "Brainstorming", "title": "Strategic Brainstorm", "points": [{"method": "Substitute", "action": "Replace manual data analysis with AI-driven insights.", "benefit": "Reduces effort, increases accuracy."}, {"method": "Combine", "action": "Integrate diverse data sources (market, financial, social).", "benefit": "Provides holistic decision context."}, {"method": "Adapt", "action": "Adapt global decision frameworks for Indian market nuances.", "benefit": "Ensures cultural relevance."}, {"method": "Modify", "action": "Gamify decision-making process for engaging user experience.", "benefit": "Boosts engagement, reduces fatigue."}]}, {"type": "solution_pivot", "label": "Strategy Pivot", "title": "The Design Logic Pivot", "pivot": {"before": "Manual data gathering, overwhelming choices, high decision anxiety.", "pivot_logic": "Leverage AI for data synthesis and present guided, personalized decision paths.", "after": "Confident, informed, efficient decision-making with clear outcomes."}}, {"type": "journey_map", "label": "Synthesize", "title": "User Journey & Friction", "stages": [{"stage": "Identify Need", "touchpoints": "Internal thought", "actions": "Realizes a decision is pending.", "emotions": "\ud83d\ude10", "friction": "Unclear problem definition."}, {"stage": "Information Search", "touchpoints": "Web, colleagues", "actions": "Gathers data from various sources.", "emotions": "\ud83d\ude15", "friction": "Information overload, conflicting data."}, {"stage": "Analysis Paralysis", "touchpoints": "Mind, notes", "actions": "Struggles to synthesize information.", "emotions": "\ud83d\ude1f", "friction": "Lack of clear framework."}, {"stage": "Decision Attempt", "touchpoints": "Self-reflection", "actions": "Tries to weigh pros and cons.", "emotions": "\ud83d\ude25", "friction": "Fear of making wrong choice."}, {"stage": "Outcome", "touchpoints": "Result", "actions": "Experiences consequences of choice.", "emotions": "\ud83c\udf89", "friction": "Post-decision regret."}]}, {"type": "wireframes", "label": "Ideation", "title": "Structural Wireframes", "screens": [{"title": "Onboarding Flow", "platform": "mobile", "layout": ["Splash Screen", "Value Proposition", "Login/Signup"]}]}, {"type": "ui_preview", "label": "Final Implementation", "title": "High-Fidelity Interface", "device_type": "iphone", "screenshot_url": "/static/output/ui_c770d78d-0c21-4590-97a1-9b94bcb1c4a7.png", "annotations": [{"title": "Drag to Login", "rationale": "Unique, engaging login interaction. Reduces friction.", "x": 50, "y": 75}, {"title": "Value Proposition", "rationale": "Clear 'Decision Enabler' text sets user expectation.", "x": 50, "y": 60}, {"title": "Minimalist UI", "rationale": "Reduces cognitive load. Focuses user on core message.", "x": 50, "y": 40}]}, {"type": "heuristic_evaluation", "label": "Expert Audit", "title": "Heuristic Evaluation", "data": [{"heuristic": "Visibility", "severity": 1, "finding": "Login action 'Drag right to login G+' is clear.", "status": "Pass"}, {"heuristic": "Consistency", "severity": 3, "finding": "Hard to judge consistency from single screen.", "status": "Warning"}, {"heuristic": "Error Prev", "severity": 1, "finding": "Drag gesture prevents accidental taps.", "status": "Pass"}, {"heuristic": "Flexibility", "severity": 4, "finding": "Only G+ login shown, limits user options.", "status": "Issue"}]}, {"type": "usability_testing", "label": "Validation", "title": "Usability Testing Results", "data": {}}], "metrics": []}